winzy_notify/__init__.py
winzy_notify-0.0.1.dist-info/LICENSE
winzy_notify-0.0.1.dist-info/METADATA
winzy_notify-0.0.1.dist-info/WHEEL
winzy_notify-0.0.1.dist-info/entry_points.txt
winzy_notify-0.0.1.dist-info/top_level.txt
winzy_notify-0.0.1.dist-info/RECORD
