Metadata-Version: 2.1
Name: winzy-notify
Version: 0.0.1
Summary: Notify in mac and windows
Author: Sukhbinder Singh
License: Apache-2.0
Project-URL: Homepage, https://github.com/sukhbinder/winzy-notify
Project-URL: Changelog, https://github.com/sukhbinder/winzy-notify/releases
Project-URL: Issues, https://github.com/sukhbinder/winzy-notify/issues
Project-URL: CI, https://github.com/sukhbinder/winzy-notify/actions
Classifier: License :: OSI Approved :: Apache Software License
License-File: LICENSE
Requires-Dist: winzy
Provides-Extra: test
Requires-Dist: pytest; extra == "test"
